kodeagent/__init__.py
kodeagent/_version.py
kodeagent/code_reviewer.py
kodeagent/code_runner.py
kodeagent/file_tracker.py
kodeagent/history_formatter.py
kodeagent/kodeagent.py
kodeagent/kutils.py
kodeagent/models.py
kodeagent/orchestrator.py
kodeagent/pattern_detector.py
kodeagent/tools.py
kodeagent/tracer.py
kodeagent/usage_tracker.py
kodeagent/prompts/agent_plan.txt
kodeagent/prompts/code_guardrail.txt
kodeagent/prompts/contextual_summary.txt
kodeagent/prompts/observation.txt
kodeagent/prompts/relevant_tools.txt
kodeagent/prompts/salvage_response.txt
kodeagent/prompts/update_plan.txt
kodeagent/prompts/system/codeact.txt
kodeagent/prompts/system/observer.txt
kodeagent/prompts/system/plan_updater.txt
kodeagent/prompts/system/planner.txt
kodeagent/prompts/system/react.txt
kodeagent-0.9.1.dist-info/licenses/LICENSE
kodeagent-0.9.1.dist-info/METADATA
kodeagent-0.9.1.dist-info/WHEEL
kodeagent-0.9.1.dist-info/top_level.txt
kodeagent-0.9.1.dist-info/RECORD
