Metadata-Version: 2.4
Name: kodeagent
Version: 0.9.1
Summary: A minimalistic approach to building AI agents
Author-email: Barun Saha <your.email@example.com>
Project-URL: Homepage, https://github.com/barun-saha/kodeagent
Project-URL: Bug Tracker, https://github.com/barun-saha/kodeagent/issues
Classifier: Programming Language :: Python :: 3
Classifier: License :: OSI Approved :: Apache Software License
Classifier: Operating System :: OS Independent
Requires-Python: >=3.10
License-File: LICENSE
Requires-Dist: litellm~=1.81.5
Requires-Dist: pydantic~=2.12.5
Requires-Dist: python-dotenv~=1.2.1
Requires-Dist: e2b-code-interpreter~=2.4.1
Requires-Dist: requests~=2.32.5
Requires-Dist: json_repair~=0.55.1
Requires-Dist: tenacity~=9.1.2
Requires-Dist: aiohttp~=3.13.3
Requires-Dist: protobuf~=6.33.5
Requires-Dist: h11~=0.16.0
Requires-Dist: rich~=14.3.1
Requires-Dist: ddgs~=9.10.0
Requires-Dist: beautifulsoup4~=4.14.3
Requires-Dist: markitdown[docx,pdf,xlsx]~=0.1.4
Requires-Dist: youtube-transcript-api~=1.2.4
Requires-Dist: wikipedia~=1.4.0
Requires-Dist: arxiv~=2.4.0
Requires-Dist: urllib3~=2.6.3
Requires-Dist: langfuse<3,>=2
Dynamic: license-file
